blingfire/__init__.py
blingfire/bert_base_cased_tok.bin
blingfire/bert_base_cased_tok.i2w
blingfire/bert_base_tok.bin
blingfire/bert_base_tok.i2w
blingfire/bert_chinese.bin
blingfire/bert_chinese.i2w
blingfire/bert_multi_cased.bin
blingfire/bert_multi_cased.i2w
blingfire/blingfiretokdll.pdb
blingfire/gpt2.bin
blingfire/gpt2.i2w
blingfire/laser100k.bin
blingfire/laser100k.i2w
blingfire/laser250k.bin
blingfire/laser250k.i2w
blingfire/laser500k.bin
blingfire/laser500k.i2w
blingfire/roberta.bin
blingfire/roberta.i2w
blingfire/syllab.bin
blingfire/uri100k.bin
blingfire/uri100k.i2w
blingfire/uri250k.bin
blingfire/uri250k.i2w
blingfire/uri500k.bin
blingfire/uri500k.i2w
blingfire/wbd_chuni.bin
blingfire/xlm_roberta_base.bin
blingfire/xlm_roberta_base.i2w
blingfire/xlnet.bin
blingfire/xlnet.i2w
blingfire/xlnet_nonorm.bin
blingfire/xlnet_nonorm.i2w
blingfire/linux/64/libblingfiretokdll.so
blingfire/linux/arm64/libblingfiretokdll.so
blingfire/mac/64/libblingfiretokdll.dylib
blingfire/mac/arm64/libblingfiretokdll.dylib
blingfire/win/64/blingfiretokdll.dll
blingfire/win/arm64/blingfiretokdll.dll
blingfire2-0.2.1.dist-info/licenses/LICENSE
blingfire2-0.2.1.dist-info/METADATA
blingfire2-0.2.1.dist-info/WHEEL
blingfire2-0.2.1.dist-info/top_level.txt
blingfire2-0.2.1.dist-info/RECORD
