Metadata-Version: 2.4
Name: blingfire2
Version: 0.2.1
Summary: Python wrapper of lightning fast Finite State Machine based NLP library.
Author-email: Microsoft <bling@microsoft.com>, Luca Foppiano <info@sciencialab.com>
Project-URL: Homepage, https://github.com/lfoppiano/Blingfire/
Requires-Python: >=3.0
License-File: LICENSE
Dynamic: license-file
